tests/__init__.py
tests/bibtext.py
tests/download.py
tests/extractions.py
tests/filters.py
tests/paths.py
testsmodules-0.0.1.dist-info/LICENSE
testsmodules-0.0.1.dist-info/METADATA
testsmodules-0.0.1.dist-info/WHEEL
testsmodules-0.0.1.dist-info/top_level.txt
testsmodules-0.0.1.dist-info/RECORD
