Metadata-Version: 2.1
Name: testsmodules
Version: 0.0.1
Summary: Talbots is a Python library for understanding, analyzing, and evaluating the content of text-generating systems through research papers published in scientific journals, with features such as downloading Bibtex information of research papers, downloading PDF files of research papers, data conversion, and supporting the detection of tortured phrases. In addition, it can assist you in developing and publishing your projects.
Home-page: https://bitbucket.org/tanhuynhng/talbots
Author: Tan H. Nguyen, Thien Q. Tran, Pham Ha Hai, Nguyen Huy Tan
Author-email: huynhtannguyen.my@uopeople.edu
License: GNU General Public License v3 or later (GPLv3+)
Classifier: Operating System :: MacOS
Classifier: Operating System :: Microsoft :: Windows
Classifier: Operating System :: POSIX :: Linux
Classifier: Programming Language :: Python :: 3
Classifier: Programming Language :: Python :: 3.5
Classifier: Programming Language :: Python :: 3.6
Classifier: Programming Language :: Python :: 3.7
Classifier: Programming Language :: Python :: 3.8
Classifier: Programming Language :: Python :: 3.9
Classifier: Programming Language :: Python :: 3.10
Classifier: Programming Language :: Python :: 3.11
Classifier: Environment :: Console
Classifier: License :: OSI Approved :: GNU General Public License v3 or later (GPLv3+)
Classifier: Topic :: Software Development :: Libraries :: Python Modules
Requires-Python: >=3.0
License-File: LICENSE
Requires-Dist: beautifulsoup4 ==4.11.2
Requires-Dist: bs4 ==0.0.1
Requires-Dist: certifi ==2022.12.7
Requires-Dist: charset-normalizer ==3.1.0
Requires-Dist: et-xmlfile ==1.1.0
Requires-Dist: idna ==3.4
Requires-Dist: openpyxl ==3.1.1
Requires-Dist: PyPDF2 ==3.0.1
Requires-Dist: requests ==2.28.2
Requires-Dist: soupsieve ==2.4
Requires-Dist: typing-extensions ==4.5.0
Requires-Dist: urllib3 ==1.26.14
